newbie/__init__.py
newbie/__main__.py
newbie/commands/__init__.py
newbie/commands/client.py
newbie/commands/container.py
newbie/commands/server.py
newbie/docker/__init__.py
SNL2023f-1.0.12.dist-info/LICENSE
SNL2023f-1.0.12.dist-info/METADATA
SNL2023f-1.0.12.dist-info/WHEEL
SNL2023f-1.0.12.dist-info/entry_points.txt
SNL2023f-1.0.12.dist-info/top_level.txt
SNL2023f-1.0.12.dist-info/RECORD
