Metadata-Version: 2.1
Name: SNL2023f
Version: 1.0.12
Summary: A simple port forward client and manager written in Python
Home-page: https://github.com/DoyunShin/
Author: DoyunShin
Author-email: doyun.shin@gmail.com
Classifier: Programming Language :: Python :: 3
Classifier: License :: OSI Approved :: GNU General Public License v3 (GPLv3)
Classifier: Operating System :: OS Independent
Requires-Python: >=3.5
License-File: LICENSE
Requires-Dist: prompt-toolkit
Requires-Dist: click
Requires-Dist: flask
Requires-Dist: requests
Requires-Dist: pycryptodome
